staticjinjaplus/__init__.py
staticjinjaplus/__version__.py
staticjinjaplus/cli.py
staticjinjaplus/http.py
staticjinjaplus/jinja_helpers.py
staticjinjaplus/staticjinja_helpers.py
staticjinjaplus-3.1.0.dist-info/licenses/LICENSE.md
staticjinjaplus-3.1.0.dist-info/METADATA
staticjinjaplus-3.1.0.dist-info/WHEEL
staticjinjaplus-3.1.0.dist-info/entry_points.txt
staticjinjaplus-3.1.0.dist-info/top_level.txt
staticjinjaplus-3.1.0.dist-info/RECORD
