Metadata-Version: 2.4
Name: staticjinjaplus
Version: 3.1.0
Summary: A sweet spot between staticjinja and a full-blown static site generator.
Home-page: https://github.com/EpocDotFr/staticjinjaplus
Author: Maxime "Epoc" Gross
Author-email: contact.nospam@epoc.nospam.fr
License: DBAD
Project-URL: Documentation, https://epocdotfr.github.io/staticjinjaplus/
Project-URL: Source code, https://github.com/EpocDotFr/staticjinjaplus
Project-URL: Issue tracker, https://github.com/EpocDotFr/staticjinjaplus/issues
Project-URL: Changelog, https://github.com/EpocDotFr/staticjinjaplus/releases
Keywords: static,website,site,generator,staticjinja,jinja,jinja2
Classifier: Development Status :: 5 - Production/Stable
Classifier: Operating System :: OS Independent
Classifier: Environment :: Console
Classifier: Environment :: Web Environment
Classifier: Topic :: Internet :: WWW/HTTP :: Site Management
Classifier: Topic :: Text Processing :: Markup :: XML
Classifier: Topic :: Text Processing :: Markup :: HTML
Classifier: Topic :: Text Processing :: Markup :: Markdown
Classifier: Programming Language :: Python :: 3.10
Classifier: Programming Language :: Python :: 3.11
Classifier: Programming Language :: Python :: 3.12
Classifier: Intended Audience :: Developers
Requires-Python: >=3.10
License-File: LICENSE.md
Requires-Dist: staticjinja~=5.0
Requires-Dist: webassets~=3.0
Requires-Dist: htmlmin~=0.1
Requires-Dist: rjsmin~=1.2
Requires-Dist: environs~=14.0
Requires-Dist: markdown~=3.6
Provides-Extra: dev
Requires-Dist: build~=1.2; extra == "dev"
Requires-Dist: twine~=6.0; extra == "dev"
Requires-Dist: mkdocs~=1.6; extra == "dev"
Requires-Dist: setuptools>=69; extra == "dev"
Dynamic: author
Dynamic: author-email
Dynamic: classifier
Dynamic: description
Dynamic: description-content-type
Dynamic: home-page
Dynamic: keywords
Dynamic: license
Dynamic: license-file
Dynamic: project-url
Dynamic: provides-extra
Dynamic: requires-dist
Dynamic: requires-python
Dynamic: summary
